slackn/__init__.py
slackn/cli.py
slackn/slackn.py
slackn-0.1.0.dist-info/AUTHORS.rst
slackn-0.1.0.dist-info/LICENSE
slackn-0.1.0.dist-info/METADATA
slackn-0.1.0.dist-info/WHEEL
slackn-0.1.0.dist-info/entry_points.txt
slackn-0.1.0.dist-info/top_level.txt
slackn-0.1.0.dist-info/RECORD
